qirrunner/__init__.py
qirrunner/_native.abi3.so
qirrunner/_native.pyi
qirrunner/py.typed
qirrunner.libs/libzstd-5df4f4df.so.1.4.8
qirrunner-0.9.0.dist-info/METADATA
qirrunner-0.9.0.dist-info/WHEEL
qirrunner-0.9.0.dist-info/entry_points.txt
qirrunner-0.9.0.dist-info/RECORD
qirrunner-0.9.0.dist-info/licenses/NOTICE.txt
