Metadata-Version: 2.4
Name: qirrunner
Version: 0.9.0
Classifier: License :: OSI Approved :: MIT License
Classifier: Development Status :: 3 - Alpha
Classifier: Intended Audience :: Developers
Classifier: Programming Language :: Python :: 3.9
Classifier: Programming Language :: Python :: 3.10
Classifier: Programming Language :: Python :: 3.11
Classifier: Programming Language :: Python :: 3.12
Classifier: Programming Language :: Python :: 3.13
Classifier: Programming Language :: Python
Classifier: Programming Language :: Rust
Classifier: Operating System :: MacOS
Classifier: Operating System :: Microsoft :: Windows
Classifier: Operating System :: POSIX :: Linux
Requires-Dist: pytest~=8.2.1 ; extra == 'test'
Provides-Extra: test
License-File: NOTICE.txt
Summary: JIT compiles and executes programs written in QIR (Quantum Intermediate Representation).
Home-Page: https://github.com/qir-alliance/qir-runner
Author: Microsoft
License: MIT
Requires-Python: >=3.9
Project-URL: Source Code, https://github.com/qir-alliance/qir-runner
